{
  "schemaVersion": 1,
  "moduleVersion": "0.1.32",
  "status": "ready-for-foundry-test",
  "source": {
    "name": "Snake",
    "url": "https://finalfantasyd20.com/gamemastering/bestiary/magical-beasts/viper-family/snake/",
    "image": "https://www.finalfantasyd20.com/wp-content/uploads/snake.png",
    "rawSections": {
      "HEADER": [
        "Home > Gamemastering > Bestiary > Magical Beasts > Viper Family > Snake Table of Contents This creature looks like a snake with reddish-orange scales and stark white eyes without pupils. Snake (CR 1/2)",
        "XP 200",
        "N Tiny Animal (Reptilian)",
        "Init +3; Senses Low-light vision, scent; Perception +9"
      ],
      "DEFENSE": [
        "AC 16, touch 15, flat-footed 13 (+3 dex, +1 natural, +2 size)",
        "hp 6 [10] (1d8+2)",
        "Fort +1, Ref +5, Will +1",
        "Resist Water 5",
        "Weakness Ice"
      ],
      "OFFENSE": [
        "Speed 20 ft., climb 20 ft., swim 20 ft.",
        "Melee Bite +5 (1d4-2 plus poison)",
        "Space 2.5 ft.; Reach 0 ft.",
        "Special Attacks Critical Attack"
      ],
      "STATISTICS": [
        "Str 6, Dex 17, Con 8, Int 1, Wis 13, Cha 2",
        "Base Atk +0; CMB +1; CMD 9 (can't be tripped)",
        "Feats Toughness*, Weapon Finesse *Bonus Feat",
        "Skills Acrobatics +13, Climb +11, Perception +9, Stealth +15, Swim +11; Racial Modifiers +4 Perception, +4 Stealth, +8 Acrobatics"
      ],
      "SPECIAL ABILITIES": [
        "Critical Attack (Ex) Once per day as a standard action, the snake can inflict more pain than normal. If they succeed at hitting with their bite attack, the damage is 1d4-2 x 1.5 for total damage.",
        "Familiar The master of a snake gains a +3 bonus on Bluff checks.",
        "Poison (Ex) Bite – injury; save Fort DC 9; frequency 1/round for 6 rounds; effect 1d2 Con damage; cure 1 save."
      ]
    },
    "parsed": {
      "cr": "1/2",
      "xp": 200,
      "alignment": "N",
      "size": "Tiny",
      "creatureType": "Animal [Familiar]",
      "subtypes": [
        "Reptilian"
      ],
      "initiative": 3,
      "senses": "Low-light vision, scent",
      "aura": "",
      "defense": {
        "raw": [
          "AC 16, touch 15, flat-footed 13 (+3 dex, +1 natural, +2 size)",
          "hp 6 [10] (1d8+2)",
          "Fort +1, Ref +5, Will +1",
          "Resist Water 5",
          "Weakness Ice"
        ],
        "ac": "AC 16, touch 15, flat-footed 13 (+3 dex, +1 natural, +2 size)",
        "hp": "hp 6 [10] (1d8+2)",
        "hitPoints": 6,
        "hitDice": 1,
        "saves": "Fort +1, Ref +5, Will +1",
        "defensiveAbilities": "",
        "dr": "",
        "immunities": "",
        "resistances": "Water 5",
        "weaknesses": "Ice",
        "sr": null
      },
      "offense": {
        "raw": [
          "Speed 20 ft., climb 20 ft., swim 20 ft.",
          "Melee Bite +5 (1d4-2 plus poison)",
          "Space 2.5 ft.; Reach 0 ft.",
          "Special Attacks Critical Attack"
        ],
        "speed": "20 ft., climb 20 ft., swim 20 ft.",
        "melee": "Bite +5 (1d4-2 plus poison)",
        "ranged": "",
        "space": "Space 2.5 ft.; Reach 0 ft.",
        "specialAttacks": "Critical Attack, Poison",
        "spellLines": []
      },
      "statistics": [
        "Str 6, Dex 17, Con 8, Int 1, Wis 13, Cha 2",
        "Base Atk +0; CMB +1; CMD 9 (can't be tripped)",
        "Feats Toughness*, Weapon Finesse *Bonus Feat",
        "Skills Acrobatics +13, Climb +11, Perception +9, Stealth +15, Swim +11; Racial Modifiers +4 Perception, +4 Stealth, +8 Acrobatics"
      ],
      "tactics": [],
      "ecology": [],
      "gear": [],
      "specialAbilities": [
        {
          "name": "Critical Attack",
          "type": "ex",
          "description": "Once per day as a standard action, the snake can inflict more pain than normal. If they succeed at hitting with their bite attack, the damage is 1d4-2 x 1.5 for total damage.",
          "notes": {
            "familiar": ""
          }
        },
        {
          "name": "Poison",
          "type": "ex",
          "description": "Bite – injury; save Fort DC 9; frequency 1/round for 6 rounds; effect 1d2 Con damage; cure 1 save.",
          "notes": {
            "familiar": ""
          }
        }
      ],
      "description": ""
    },
    "signals": {
      "hasMeleeAttacks": true,
      "hasRangedAttacks": false,
      "hasSpecialAttacks": true,
      "hasSpellLines": false,
      "hasFeats": true,
      "hasSpecialQualities": false,
      "hasGear": false,
      "hasSpecialAbilities": true,
      "hasDefensiveAbilities": false,
      "hasResistances": true,
      "hasImmunities": false,
      "hasWeaknesses": true,
      "hasDamageReduction": false,
      "hasSpellResistance": false,
      "hasSenses": true
    }
  },
  "foundryOutput": {
    "actorFile": "snake.json",
    "curationFile": "snake.json",
    "pack": "ffd20-expanded-bestiary_animals",
    "packLabel": "FFD20 Expanded - Animals",
    "actorType": "npc",
    "image": "modules/ffd20-expanded-bestiary/assets/creatures/snake.png",
    "tokenImage": "modules/ffd20-expanded-bestiary/assets/creatures/snake.png",
    "traits": {
      "size": "tiny",
      "senses": {
        "dv": {
          "value": 0
        },
        "ts": {
          "value": 0
        },
        "bs": {
          "value": 0
        },
        "bse": {
          "value": 0
        },
        "ll": {
          "enabled": true,
          "multiplier": {
            "dim": 2,
            "bright": 2
          }
        },
        "ls": {
          "value": 0
        },
        "sid": false,
        "tr": {
          "value": 0
        },
        "si": false,
        "sc": {
          "value": 30
        },
        "custom": ""
      },
      "dr": {
        "value": [],
        "custom": ""
      },
      "eres": {
        "value": [
          {
            "amount": 5,
            "types": [
              "water"
            ],
            "operator": true
          }
        ],
        "custom": ""
      },
      "cres": "",
      "di": [],
      "dv": [
        "ice"
      ],
      "ci": [],
      "languages": [],
      "stature": "tall"
    },
    "skills": {
      "acr": {
        "ability": "dex",
        "rank": 0
      },
      "clm": {
        "ability": "str",
        "rank": 1
      },
      "per": {
        "ability": "wis",
        "rank": 1
      },
      "ste": {
        "ability": "dex",
        "rank": 0
      },
      "swm": {
        "ability": "str",
        "rank": 1
      }
    },
    "defenses": {
      "hpAbility": "con",
      "init": {
        "value": 0,
        "ability": "dex"
      },
      "naturalAC": 1,
      "hp": {
        "temp": 0,
        "offset": 0
      },
      "mp": {
        "value": 0,
        "max": 0,
        "temp": 0,
        "recover": 0,
        "offset": 0
      },
      "hd": {
        "total": 1
      },
      "savingThrows": {
        "fort": {
          "base": 0,
          "ability": "con"
        },
        "ref": {
          "base": 0,
          "ability": "dex"
        },
        "will": {
          "base": 0,
          "ability": "wis"
        }
      },
      "speed": {
        "land": {
          "base": 20
        },
        "climb": {
          "base": 20
        },
        "swim": {
          "base": 20
        },
        "burrow": {
          "base": 0
        },
        "fly": {
          "base": 0,
          "maneuverability": "average"
        }
      },
      "sr": {
        "formula": ""
      },
      "acNotes": "",
      "cmdNotes": "Cannot be tripped."
    },
    "coverage": {
      "racialHitDice": [
        "Animal"
      ],
      "naturalAttacks": [
        "Bite"
      ],
      "weaponAttacks": [],
      "inventory": [],
      "spells": [],
      "feats": [
        "Toughness",
        "Weapon Finesse"
      ],
      "specialQualities": [],
      "specialAttacks": [],
      "defensiveAbilities": [],
      "rawSpecialAbilities": [
        "Familiar"
      ],
      "specialAbilities": [
        "Critical Attack",
        "Poison"
      ],
      "buffs": [],
      "miscellaneous": [
        "Source Statblock Adjustments",
        "Familiar Master Bonus"
      ]
    },
    "items": [
      {
        "id": "racialhd00000001",
        "name": "Animal",
        "type": "class",
        "subType": "racial",
        "category": "racialHitDice",
        "generatedFlags": [
          "generatedRacialHitDice"
        ],
        "sourceFlagData": {
          "racialProfile": "Animal"
        },
        "mechanics": {
          "actions": [],
          "changes": [
            {
              "target": "skill.per",
              "formula": "4",
              "type": "racial",
              "operator": "add"
            },
            {
              "target": "skill.ste",
              "formula": "4",
              "type": "racial",
              "operator": "add"
            },
            {
              "target": "skill.acr",
              "formula": "8",
              "type": "racial",
              "operator": "add"
            },
            {
              "target": "skill.acr",
              "formula": "2",
              "type": "untyped",
              "operator": "add"
            },
            {
              "target": "skill.clm",
              "formula": "1",
              "type": "untyped",
              "operator": "add"
            },
            {
              "target": "skill.swm",
              "formula": "1",
              "type": "untyped",
              "operator": "add"
            }
          ],
          "contextNotes": [],
          "classSkills": {
            "acr": true,
            "clm": true,
            "fly": true,
            "per": true,
            "ste": true,
            "sur": true,
            "swm": true
          },
          "level": 1,
          "hitDie": 8,
          "baseAttack": "med",
          "savingThrows": {
            "fort": {
              "value": "high"
            },
            "ref": {
              "value": "high"
            },
            "will": {
              "value": "low"
            }
          }
        },
        "reviewNotes": []
      },
      {
        "id": "srcstatadjust001",
        "name": "Source Statblock Adjustments",
        "type": "buff",
        "subType": "perm",
        "category": "buff",
        "generatedFlags": [
          "generatedSourceStatAdjustments"
        ],
        "sourceFlagData": {},
        "mechanics": {
          "actions": [],
          "changes": [
            {
              "target": "cmb",
              "formula": "5",
              "type": "untyped",
              "operator": "add"
            }
          ],
          "contextNotes": [],
          "level": 0
        },
        "reviewNotes": []
      },
      {
        "id": "natatk0000000001",
        "name": "Bite",
        "type": "attack",
        "subType": "natural",
        "category": "naturalAttacks",
        "generatedFlags": [
          "generatedNaturalAttack"
        ],
        "sourceFlagData": {
          "naturalAttack": {
            "count": 1,
            "name": "Bite",
            "ranged": false,
            "attackBonus": 5,
            "damage": "1d4-2 plus poison",
            "damageFormula": "1d4",
            "printedDamageBonus": -2,
            "damageType": "",
            "critRange": 20,
            "critMult": 2,
            "natural": true
          }
        },
        "mechanics": {
          "actions": [
            {
              "name": "Bite",
              "actionType": "mwak",
              "activation": "standard",
              "range": {
                "value": "reach",
                "units": "natural",
                "maxIncrements": 1,
                "minValue": "",
                "minUnits": ""
              },
              "target": {
                "value": "one target"
              },
              "damage": [
                {
                  "formula": "1d4",
                  "types": [
                    "piercing"
                  ]
                }
              ],
              "effectNotes": [
                "On hit: resolve Poison."
              ]
            }
          ],
          "changes": [],
          "contextNotes": []
        },
        "reviewNotes": []
      },
      {
        "id": "feat000000000001",
        "name": "Toughness",
        "type": "feat",
        "subType": "feat",
        "category": "feats",
        "generatedFlags": [
          "generatedFeat"
        ],
        "compendiumLookup": {
          "expectedTypes": [
            "feat"
          ],
          "expectedSubTypes": [
            "feat"
          ],
          "runtimeHydration": "Importer will replace this generated placeholder if a matching FFD20/PF item is found."
        },
        "sourceFlagData": {},
        "mechanics": {
          "actions": [],
          "changes": [],
          "contextNotes": [],
          "classSkills": {}
        },
        "reviewNotes": []
      },
      {
        "id": "feat000000000002",
        "name": "Weapon Finesse",
        "type": "feat",
        "subType": "feat",
        "category": "feats",
        "generatedFlags": [
          "generatedFeat"
        ],
        "compendiumLookup": {
          "expectedTypes": [
            "feat"
          ],
          "expectedSubTypes": [
            "feat"
          ],
          "runtimeHydration": "Importer will replace this generated placeholder if a matching FFD20/PF item is found."
        },
        "sourceFlagData": {},
        "mechanics": {
          "actions": [],
          "changes": [],
          "contextNotes": [],
          "classSkills": {}
        },
        "reviewNotes": []
      },
      {
        "id": "rfeat00000000001",
        "name": "Familiar",
        "type": "feat",
        "subType": "racial",
        "category": "rawSpecialAbilities",
        "generatedFlags": [
          "generatedRawSpecialAbility"
        ],
        "sourceFlagData": {
          "customFeature": true
        },
        "mechanics": {
          "actions": [],
          "changes": [],
          "contextNotes": [
            {
              "target": "misc",
              "text": "Familiar master bonus; apply this to the master, not to the creature."
            }
          ],
          "classSkills": {}
        },
        "reviewNotes": []
      },
      {
        "id": "sa00000000000001",
        "name": "Critical Attack",
        "type": "feat",
        "subType": "racial",
        "category": "specialAbilities",
        "generatedFlags": [
          "specialAbility"
        ],
        "sourceFlagData": {
          "specialAbility": {
            "category": "toggle",
            "sourceType": "Ex",
            "saveDCs": [],
            "damages": [],
            "healing": [],
            "uses": {
              "value": 1,
              "per": "day",
              "maxFormula": "1",
              "rechargeFormula": ""
            },
            "criticalAttack": {
              "attackName": "bite",
              "damageFormula": "floor((1d4-2) * 1.5)",
              "sourceDamageFormula": "1d4-2",
              "multiplier": "1.5",
              "raw": "damage is 1d4-2 x 1.5"
            }
          }
        },
        "mechanics": {
          "actions": [
            {
              "name": "Critical Attack",
              "actionType": "mwak",
              "activation": "standard",
              "range": {
                "value": "reach",
                "units": "natural",
                "maxIncrements": 1,
                "minValue": "",
                "minUnits": ""
              },
              "target": {
                "value": "one target"
              },
              "damage": [
                {
                  "formula": "floor((1d4 + floor(@abilities.str.mod * 1)) * 1.5)",
                  "types": [
                    "piercing"
                  ]
                }
              ],
              "effectNotes": [
                "Once per day as a standard action, the snake can inflict more pain than normal. If they succeed at hitting with their bite attack, the damage is 1d4-2 x 1.5 for total damage.",
                "Uses Bite attack.",
                "Source damage: damage is 1d4-2 x 1.5.",
                "Dynamic damage: source -2 derived as floor(@abilities.str.mod * 1)."
              ]
            }
          ],
          "changes": [],
          "contextNotes": [],
          "classSkills": {}
        },
        "reviewNotes": []
      },
      {
        "id": "sa00000000000002",
        "name": "Poison",
        "type": "feat",
        "subType": "racial",
        "category": "specialAbilities",
        "generatedFlags": [
          "specialAbility"
        ],
        "sourceFlagData": {
          "specialAbility": {
            "category": "passive",
            "sourceType": "Ex",
            "saveDCs": [
              {
                "save": "fort",
                "dc": 9,
                "raw": "Fort DC 9",
                "formula": "10 + floor(@attributes.hd.total / 2) + @abilities.con.mod",
                "ability": "con",
                "confidence": "default-ex-con-floor",
                "base": 10,
                "expectedDc": 9
              }
            ],
            "damages": [
              {
                "formula": "1d2",
                "type": "con",
                "raw": "1d2 Con damage"
              }
            ],
            "healing": []
          }
        },
        "mechanics": {
          "actions": [
            {
              "name": "Poison",
              "actionType": "save",
              "activation": "standard",
              "touch": false,
              "range": {
                "value": null,
                "units": ""
              },
              "target": {
                "value": ""
              },
              "damage": [
                {
                  "formula": "1d2",
                  "types": [
                    "con"
                  ]
                }
              ],
              "save": {
                "type": "fort",
                "dc": "10 + floor(@attributes.hd.total / 2) + @abilities.con.mod",
                "description": "Negates poison"
              },
              "effectNotes": [
                "Bite – injury; save Fort DC 9; frequency 1/round for 6 rounds; effect 1d2 Con damage; cure 1 save.",
                "Duration: 6 rounds"
              ]
            }
          ],
          "changes": [],
          "contextNotes": [],
          "classSkills": {}
        },
        "reviewNotes": []
      },
      {
        "id": "famaster00000001",
        "name": "Familiar Master Bonus",
        "type": "buff",
        "subType": "temp",
        "category": "buff",
        "generatedFlags": [],
        "sourceFlagData": {},
        "mechanics": {
          "actions": [],
          "changes": [
            {
              "target": "skill.blf",
              "formula": "3",
              "type": "untyped",
              "operator": "add"
            }
          ],
          "contextNotes": [
            {
              "target": "misc",
              "text": "This buff belongs on the familiar's master, not the familiar."
            }
          ],
          "level": 0
        },
        "reviewNotes": []
      }
    ]
  },
  "curation": {
    "summary": "Snake is packaged as an FFD20 NPC actor with 9 generated item(s) across 6 populated mechanics categories.",
    "creatureRole": {
      "cr": "1/2",
      "size": "Tiny",
      "type": "Animal [Familiar]",
      "alignment": "N",
      "primarySourceAttacks": [
        "Bite +5 (1d4-2 plus poison)"
      ],
      "specialAbilityNames": [
        "Critical Attack",
        "Poison",
        "Familiar"
      ]
    },
    "rulesDecisions": [
      "Actor data preserves the source statblock in biography and builder flags before any Foundry runtime hydration.",
      "Only true feats, spells, and inventory placeholders are eligible for compendium lookup during import; creature-specific special abilities remain custom generated features.",
      "Racial hit dice are generated from the creature type and source hit dice instead of creating class levels.",
      "Source defensive text is mapped into FFD20 trait fields while unusual FF defenses remain preserved as custom text.",
      "Natural attack items use source attack totals, source damage dice, and manual extra attacks for full-attack routines.",
      "Skill ranks are reverse-calculated from source totals after ability modifiers, racial modifiers, size modifiers, and class-skill bonuses."
    ],
    "unresolved": [],
    "nextReviewSteps": [
      "Import into Foundry and verify compendium hydration results.",
      "Spot-check the actor sheet tabs for attacks, feats, skills, buffs, defenses, and biography source text."
    ]
  }
}