{
  "name": "Hatchling Black Dragon",
  "type": "npc",
  "img": "modules/ffd20-expanded-bestiary/assets/creatures/hatchling-black-dragon.png",
  "system": {
    "abilities": {
      "str": {
        "value": 10,
        "damage": 0,
        "drain": 0,
        "userPenalty": 0
      },
      "dex": {
        "value": 16,
        "damage": 0,
        "drain": 0,
        "userPenalty": 0
      },
      "con": {
        "value": 10,
        "damage": 0,
        "drain": 0,
        "userPenalty": 0
      },
      "int": {
        "value": 9,
        "damage": 0,
        "drain": 0,
        "userPenalty": 0
      },
      "wis": {
        "value": 8,
        "damage": 0,
        "drain": 0,
        "userPenalty": 0
      },
      "cha": {
        "value": 14,
        "damage": 0,
        "drain": 0,
        "userPenalty": 0
      }
    },
    "attributes": {
      "init": {
        "value": 7,
        "ability": "dex"
      },
      "naturalAC": 1,
      "hp": {
        "value": 25,
        "max": 25,
        "temp": 0,
        "offset": 0
      },
      "mp": {
        "value": 0,
        "max": 0,
        "temp": 0,
        "recover": 0,
        "offset": 0
      },
      "hd": {
        "total": 3
      },
      "savingThrows": {
        "fort": {
          "value": 3,
          "ability": "con"
        },
        "ref": {
          "value": 8,
          "ability": "dex"
        },
        "will": {
          "value": 2,
          "ability": "wis"
        }
      },
      "speed": {
        "land": {
          "base": 60
        },
        "climb": {
          "base": 0
        },
        "swim": {
          "base": 0
        },
        "burrow": {
          "base": 0
        },
        "fly": {
          "base": 100,
          "maneuverability": "average"
        }
      },
      "sr": {
        "formula": ""
      }
    },
    "skills": {
      "fly": {
        "ability": "dex",
        "rank": 3
      },
      "per": {
        "ability": "wis",
        "rank": 4
      },
      "spl": {
        "ability": "int",
        "rank": 3
      },
      "ste": {
        "ability": "dex",
        "rank": 0
      },
      "sur": {
        "ability": "wis",
        "rank": 3
      }
    },
    "details": {
      "xp": {
        "value": 600
      },
      "cr": {
        "base": 2
      },
      "biography": {
        "value": "<h2>Defense</h2><p>AC 16, touch 15, flat-footed 13 (+3 dex, +1 natural, +2 size)</p><p>hp 25 (3d12)</p><p>Fort +3, Ref +8, Will +2</p><p>Immune Shadow, Paralysis, Sleep</p><p>Weakness Holy</p><h2>Offense</h2><p>Speed 60 ft., fly 100 ft. (average)</p><p>Melee Bite +5 (1d4), 2 Claws +5 (1d3)</p><p>Space 2.5 ft.; Reach 0 ft. (2.5 ft. with bite)</p><p>Special Attacks Breath Weapon (30-ft. line, 1d10 shadow damage, Reflex DC 11 half, usable every 1d4 rounds) Special Abilities Terror Touch</p><h2>Statistics</h2><p>Str 10, Dex 16, Con 10, Int 9, Wis 8, Cha 14</p><p>Base Atk +3; CMB +4; CMD 14 (18 vs. trip)</p><p>Feats Improved Initiative, Lightning Reflexes</p><p>Skills Fly +13, Perception +6, Spellcraft +5, Stealth +21, Survival +5; Racial Modifiers +8 Stealth</p><p>Languages Draconic</p>"
      }
    },
    "traits": {
      "size": "tiny",
      "senses": {
        "dv": {
          "value": 0
        },
        "ts": {
          "value": 0
        },
        "bs": {
          "value": 0
        },
        "bse": {
          "value": 0
        },
        "ll": {
          "enabled": false,
          "multiplier": {
            "dim": 2,
            "bright": 2
          }
        },
        "ls": {
          "value": 0
        },
        "sid": true,
        "tr": {
          "value": 0
        },
        "si": false,
        "sc": {
          "value": 0
        },
        "custom": "Dragon senses, see in darkness"
      },
      "dr": {
        "value": [],
        "custom": ""
      },
      "eres": {
        "value": [],
        "custom": ""
      },
      "cres": "",
      "di": [
        "Shadow",
        "Paralysis",
        "Sleep"
      ],
      "dv": [
        "Holy"
      ],
      "ci": [],
      "languages": [
        "Draconic"
      ],
      "stature": "tall"
    },
    "currency": {
      "pp": 0,
      "gp": 0,
      "sp": 0,
      "cp": 0
    },
    "altCurrency": {
      "pp": 0,
      "gp": 0,
      "sp": 0,
      "cp": 0
    }
  },
  "items": [
    {
      "_id": "racialhd00000001",
      "name": "Dragon",
      "type": "class",
      "img": "systems/ffd20/icons/skills/yellow_08.jpg",
      "system": {
        "description": {
          "value": "<p>Generated racial hit dice from the source statblock.</p>",
          "instructions": ""
        },
        "changes": [
          {
            "formula": "8",
            "target": "skill.ste",
            "type": "racial",
            "operator": "add",
            "priority": 0
          }
        ],
        "contextNotes": [],
        "links": {
          "classAssociations": []
        },
        "tag": "dragon",
        "subType": "racial",
        "classSubType": "racial",
        "parentClass": "",
        "level": 3,
        "hd": 12,
        "hp": 25,
        "classCastingStat": "noncaster",
        "classBaseMPTypes": "noncaster",
        "classBaseMPauto": "yes",
        "mp": 0,
        "bab": "high",
        "skillsPerLevel": 6,
        "savingThrows": {
          "fort": {
            "value": "high"
          },
          "ref": {
            "value": "high"
          },
          "will": {
            "value": "high"
          }
        },
        "fc": {
          "hp": {
            "value": 0
          },
          "skill": {
            "value": 0
          },
          "alt": {
            "value": 0,
            "notes": ""
          }
        },
        "wealth": "",
        "alignment": "N/NE",
        "classSkills": {
          "apr": true,
          "blf": true,
          "clm": true,
          "dip": true,
          "fly": true,
          "hea": true,
          "int": true,
          "kar": true,
          "khi": true,
          "klo": true,
          "kna": true,
          "kpl": true,
          "kre": true,
          "per": true,
          "sen": true,
          "spl": true,
          "ste": true,
          "sur": true,
          "swm": true,
          "umd": true
        },
        "armorProf": [],
        "weaponProf": [],
        "languages": [],
        "flags": {
          "boolean": {},
          "dictionary": {}
        },
        "scriptCalls": []
      },
      "flags": {
        "ffd20-bestiary-builder": {
          "generatedRacialHitDice": true,
          "profile": "Dragon",
          "sourceHitPoints": 25,
          "sourceHitDice": 3,
          "spellcasting": null
        }
      }
    },
    {
      "_id": "natatk0000000001",
      "name": "Bite",
      "type": "attack",
      "img": "systems/ffd20/icons/skills/red_30.jpg",
      "system": {
        "description": {
          "value": "<p>Generated from the source statblock melee attack line.</p>",
          "instructions": ""
        },
        "actions": [
          {
            "name": "Bite",
            "img": "systems/ffd20/icons/skills/red_30.jpg",
            "activation": {
              "cost": 1,
              "type": "standard",
              "unchained": {
                "cost": 1,
                "type": "action"
              }
            },
            "target": {
              "value": "one target"
            },
            "range": {
              "value": "reach",
              "units": "natural",
              "maxIncrements": 1,
              "minValue": "",
              "minUnits": ""
            },
            "actionType": "mwak",
            "attackBonus": "",
            "damage": {
              "parts": [
                {
                  "formula": "1d4",
                  "types": [
                    "piercing"
                  ]
                }
              ],
              "critParts": [],
              "nonCritParts": []
            },
            "extraAttacks": {
              "type": "",
              "manual": [],
              "formula": {
                "count": "",
                "bonus": "",
                "label": ""
              }
            },
            "ability": {
              "attack": "str",
              "damage": "str",
              "damageMult": 1,
              "max": null,
              "critRange": 20,
              "critMult": 2
            },
            "save": {
              "dc": "",
              "type": "",
              "description": "",
              "harmless": false
            },
            "naturalAttack": {
              "primary": true,
              "secondary": {
                "attackBonus": "",
                "damageMult": 0.5
              }
            },
            "attackName": "Bite",
            "critConfirmBonus": "",
            "notes": {
              "effect": [],
              "footer": [
                "Source statblock: Bite +5 (1d4)"
              ]
            },
            "measureTemplate": {
              "type": "",
              "size": ""
            }
          }
        ],
        "attackNotes": [],
        "effectNotes": [],
        "links": {
          "charges": []
        },
        "tag": "bite",
        "subType": "natural",
        "baseTypes": [],
        "broken": false,
        "weaponGroups": [],
        "showInQuickbar": true,
        "uses": {
          "value": null,
          "per": "",
          "autoDeductChargesCost": "",
          "maxFormula": "",
          "rechargeFormula": ""
        },
        "proficient": true,
        "held": "",
        "ammo": {
          "type": "",
          "capacity": null,
          "misfire": null,
          "explode": null
        },
        "enh": null,
        "flags": {
          "boolean": {},
          "dictionary": {}
        },
        "scriptCalls": []
      },
      "flags": {
        "ffd20-bestiary-builder": {
          "generatedNaturalAttack": {
            "count": 1,
            "name": "Bite",
            "ranged": false,
            "attackBonus": 5,
            "damage": "1d4",
            "damageFormula": "1d4",
            "printedDamageBonus": 0,
            "natural": true
          }
        }
      }
    },
    {
      "_id": "natatk0000000002",
      "name": "Claw x2",
      "type": "attack",
      "img": "systems/ffd20/icons/skills/red_30.jpg",
      "system": {
        "description": {
          "value": "<p>Generated from the source statblock melee attack line.</p>",
          "instructions": ""
        },
        "actions": [
          {
            "name": "Claw",
            "img": "systems/ffd20/icons/skills/red_30.jpg",
            "activation": {
              "cost": 1,
              "type": "standard",
              "unchained": {
                "cost": 1,
                "type": "action"
              }
            },
            "target": {
              "value": "one target"
            },
            "range": {
              "value": "reach",
              "units": "natural",
              "maxIncrements": 1,
              "minValue": "",
              "minUnits": ""
            },
            "actionType": "mwak",
            "attackBonus": "",
            "damage": {
              "parts": [
                {
                  "formula": "1d3",
                  "types": [
                    "slashing"
                  ]
                }
              ],
              "critParts": [],
              "nonCritParts": []
            },
            "extraAttacks": {
              "type": "",
              "manual": [
                {
                  "formula": "0",
                  "name": "Claw 2"
                }
              ],
              "formula": {
                "count": "",
                "bonus": "",
                "label": ""
              }
            },
            "ability": {
              "attack": "str",
              "damage": "str",
              "damageMult": 1,
              "max": null,
              "critRange": 20,
              "critMult": 2
            },
            "save": {
              "dc": "",
              "type": "",
              "description": "",
              "harmless": false
            },
            "naturalAttack": {
              "primary": true,
              "secondary": {
                "attackBonus": "",
                "damageMult": 0.5
              }
            },
            "attackName": "Claw",
            "critConfirmBonus": "",
            "notes": {
              "effect": [],
              "footer": [
                "Source statblock: 2 Claw +5 (1d3)"
              ]
            },
            "measureTemplate": {
              "type": "",
              "size": ""
            }
          }
        ],
        "attackNotes": [],
        "effectNotes": [],
        "links": {
          "charges": []
        },
        "tag": "claw",
        "subType": "natural",
        "baseTypes": [],
        "broken": false,
        "weaponGroups": [],
        "showInQuickbar": true,
        "uses": {
          "value": null,
          "per": "",
          "autoDeductChargesCost": "",
          "maxFormula": "",
          "rechargeFormula": ""
        },
        "proficient": true,
        "held": "",
        "ammo": {
          "type": "",
          "capacity": null,
          "misfire": null,
          "explode": null
        },
        "enh": null,
        "flags": {
          "boolean": {},
          "dictionary": {}
        },
        "scriptCalls": []
      },
      "flags": {
        "ffd20-bestiary-builder": {
          "generatedNaturalAttack": {
            "count": 2,
            "name": "Claw",
            "ranged": false,
            "attackBonus": 5,
            "damage": "1d3",
            "damageFormula": "1d3",
            "printedDamageBonus": 0,
            "natural": true
          }
        }
      }
    },
    {
      "_id": "feat000000000001",
      "name": "Improved Initiative",
      "type": "feat",
      "img": "systems/ffd20/icons/skills/yellow_36.jpg",
      "system": {
        "description": {
          "value": "<p>Generated feat from the source statblock: Improved Initiative.</p>",
          "instructions": ""
        },
        "actions": [],
        "attackNotes": [],
        "effectNotes": [],
        "uses": {
          "value": null,
          "per": "",
          "autoDeductChargesCost": "",
          "maxFormula": "",
          "rechargeFormula": ""
        },
        "changes": [],
        "contextNotes": [],
        "links": {
          "charges": []
        },
        "tag": "improved-initiative",
        "subType": "feat",
        "traitType": "",
        "traitCategory": "",
        "racePoints": null,
        "abilityType": "na",
        "associations": {
          "classes": []
        },
        "showInQuickbar": false,
        "crOffset": "",
        "inherited": false,
        "acquired": false,
        "simple": false,
        "summons": false,
        "disabled": false,
        "classSkills": {}
      },
      "flags": {
        "ffd20-bestiary-builder": {
          "generatedFeat": true,
          "lookupTypes": [
            "feat"
          ],
          "lookupSubTypes": [
            "feat"
          ],
          "sourceLine": "Feats Improved Initiative, Lightning Reflexes"
        }
      }
    },
    {
      "_id": "feat000000000002",
      "name": "Lightning Reflexes",
      "type": "feat",
      "img": "systems/ffd20/icons/skills/yellow_36.jpg",
      "system": {
        "description": {
          "value": "<p>Generated feat from the source statblock: Lightning Reflexes.</p>",
          "instructions": ""
        },
        "actions": [],
        "attackNotes": [],
        "effectNotes": [],
        "uses": {
          "value": null,
          "per": "",
          "autoDeductChargesCost": "",
          "maxFormula": "",
          "rechargeFormula": ""
        },
        "changes": [],
        "contextNotes": [],
        "links": {
          "charges": []
        },
        "tag": "lightning-reflexes",
        "subType": "feat",
        "traitType": "",
        "traitCategory": "",
        "racePoints": null,
        "abilityType": "na",
        "associations": {
          "classes": []
        },
        "showInQuickbar": false,
        "crOffset": "",
        "inherited": false,
        "acquired": false,
        "simple": false,
        "summons": false,
        "disabled": false,
        "classSkills": {}
      },
      "flags": {
        "ffd20-bestiary-builder": {
          "generatedFeat": true,
          "lookupTypes": [
            "feat"
          ],
          "lookupSubTypes": [
            "feat"
          ],
          "sourceLine": "Feats Improved Initiative, Lightning Reflexes"
        }
      }
    },
    {
      "_id": "spatk00000000001",
      "name": "Breath Weapon",
      "type": "feat",
      "img": "systems/ffd20/icons/skills/red_30.jpg",
      "system": {
        "description": {
          "value": "<p>Special attack listed in the source statblock: Breath Weapon (30-ft. line, 1d10 shadow damage, Reflex DC 11 half, usable every 1d4 rounds).</p>",
          "instructions": ""
        },
        "actions": [
          {
            "name": "Breath Weapon",
            "actionType": "save",
            "activation": {
              "cost": 1,
              "type": "standard",
              "unchained": {
                "cost": 1,
                "type": "action"
              }
            },
            "range": {
              "value": 30,
              "units": "ft"
            },
            "target": {
              "value": "30-ft. line"
            },
            "attackBonus": "",
            "touch": false,
            "damage": {
              "critParts": [],
              "nonCritParts": [],
              "parts": [
                {
                  "formula": "1d10",
                  "types": [
                    "shadow"
                  ]
                }
              ]
            },
            "save": {
              "dc": "10 + floor(@attributes.hd.total / 2) + @abilities.con.mod",
              "type": "ref",
              "description": ""
            },
            "notes": {
              "effect": [
                "Area: 30-ft. line",
                "Recharge [[1d4]] rounds."
              ],
              "footer": []
            },
            "effectNotes": [
              "Area: 30-ft. line",
              "Recharge [[1d4]] rounds."
            ],
            "measureTemplate": {
              "type": "",
              "size": null
            }
          }
        ],
        "attackNotes": [],
        "effectNotes": [],
        "uses": {
          "value": 1,
          "per": "",
          "maxFormula": "1",
          "rechargeFormula": "1d4",
          "rechargePeriod": "rounds"
        },
        "changes": [],
        "contextNotes": [],
        "links": {
          "charges": []
        },
        "tag": "breath-weapon",
        "subType": "racial",
        "traitType": "",
        "traitCategory": "",
        "racePoints": null,
        "abilityType": "na",
        "associations": {
          "classes": []
        },
        "showInQuickbar": false,
        "crOffset": "",
        "inherited": false,
        "acquired": false,
        "simple": false,
        "summons": false,
        "disabled": false,
        "classSkills": {}
      },
      "flags": {
        "ffd20-bestiary-builder": {
          "generatedSpecialAttack": true,
          "customFeature": true,
          "sourceText": "Breath Weapon (30-ft. line, 1d10 shadow damage, Reflex DC 11 half, usable every 1d4 rounds)",
          "specialAbility": {
            "category": "passive",
            "buff": null,
            "uses": {
              "value": 1,
              "per": "",
              "maxFormula": "1",
              "rechargeFormula": "1d4",
              "rechargePeriod": "rounds"
            },
            "saveDCs": [
              {
                "save": "ref",
                "dc": 11,
                "raw": "Reflex DC 11",
                "formula": "10 + floor(@attributes.hd.total / 2) + @abilities.con.mod",
                "ability": "con",
                "confidence": "default-na-con-floor",
                "base": 11,
                "expectedDc": 11
              }
            ],
            "damages": [
              {
                "formula": "1d10",
                "type": "shadow",
                "raw": "1d10 shadow damage"
              }
            ],
            "healing": [],
            "attack": null,
            "activation": {
              "cost": 1,
              "type": "standard",
              "unchained": {
                "cost": 1,
                "type": "action"
              }
            },
            "criticalAttack": null,
            "requiresSave": false,
            "saveType": null,
            "blueMage": "",
            "range": {
              "value": null,
              "units": ""
            },
            "target": {
              "value": ""
            },
            "duration": null,
            "abilityScores": {
              "str": {
                "value": 10,
                "mod": 0,
                "missing": false,
                "raw": "10"
              },
              "dex": {
                "value": 16,
                "mod": 3,
                "missing": false,
                "raw": "16"
              },
              "con": {
                "value": 10,
                "mod": 0,
                "missing": false,
                "raw": "10"
              },
              "int": {
                "value": 9,
                "mod": -1,
                "missing": false,
                "raw": "9"
              },
              "wis": {
                "value": 8,
                "mod": -1,
                "missing": false,
                "raw": "8"
              },
              "cha": {
                "value": 14,
                "mod": 2,
                "missing": false,
                "raw": "14"
              }
            }
          }
        }
      }
    },
    {
      "_id": "sa00000000000001",
      "name": "See in Darkness",
      "type": "feat",
      "img": "systems/ffd20/icons/skills/yellow_36.jpg",
      "system": {
        "description": {
          "value": "<p>A black dragon can see perfectly in darkness of any kind, including that created by the blacklight spell.</p>",
          "instructions": ""
        },
        "actions": [],
        "attackNotes": [],
        "effectNotes": [],
        "uses": {
          "value": null,
          "per": "",
          "autoDeductChargesCost": "",
          "maxFormula": "",
          "rechargeFormula": ""
        },
        "changes": [],
        "contextNotes": [
          {
            "target": "misc",
            "text": "Can see perfectly in darkness, including magical darkness."
          }
        ],
        "links": {
          "charges": []
        },
        "tag": "see-in-darkness",
        "subType": "racial",
        "traitType": "",
        "traitCategory": "",
        "racePoints": null,
        "abilityType": "su",
        "associations": {
          "classes": []
        },
        "showInQuickbar": false,
        "crOffset": "",
        "inherited": false,
        "acquired": false,
        "simple": false,
        "summons": false,
        "disabled": false,
        "classSkills": {}
      },
      "flags": {
        "ffd20-bestiary-builder": {
          "specialAbility": {
            "category": "passive",
            "buff": {
              "active": true,
              "changes": [],
              "contextNotes": [
                {
                  "target": "misc",
                  "text": "Can see perfectly in darkness, including magical darkness."
                }
              ],
              "automationNotes": []
            },
            "uses": null,
            "saveDCs": [],
            "damages": [],
            "healing": [],
            "attack": null,
            "activation": {
              "cost": 1,
              "type": "standard",
              "unchained": {
                "cost": 1,
                "type": "action"
              }
            },
            "criticalAttack": null,
            "requiresSave": false,
            "saveType": null,
            "blueMage": "",
            "range": {
              "value": null,
              "units": ""
            },
            "target": {
              "value": ""
            },
            "duration": null,
            "abilityScores": {
              "str": {
                "value": 10,
                "mod": 0,
                "missing": false,
                "raw": "10"
              },
              "dex": {
                "value": 16,
                "mod": 3,
                "missing": false,
                "raw": "16"
              },
              "con": {
                "value": 10,
                "mod": 0,
                "missing": false,
                "raw": "10"
              },
              "int": {
                "value": 9,
                "mod": -1,
                "missing": false,
                "raw": "9"
              },
              "wis": {
                "value": 8,
                "mod": -1,
                "missing": false,
                "raw": "8"
              },
              "cha": {
                "value": 14,
                "mod": 2,
                "missing": false,
                "raw": "14"
              }
            },
            "sourceType": "Su"
          }
        }
      }
    },
    {
      "_id": "sa00000000000002",
      "name": "Terror Touch",
      "type": "feat",
      "img": "systems/ffd20/icons/skills/yellow_36.jpg",
      "system": {
        "description": {
          "value": "<p>Once every 1d4 rounds as a standard action, a black dragon reaches out with terror towards an opponent within 35 feet. The affected creature becomes frightened for 1d4 rounds. A frightened creature flees from the source of its fear as best it can. If unable to flee, it may fight. A frightened creature takes a –2 penalty on all attack rolls, saving throws, skill checks, and ability checks. A frightened creature can use special abilities, including spells, to flee; indeed, the creature must use such means if they are the only way to escape. If the subject succeeds on a Will save (DC 13), it is shaken for 1 round. Blue mages may learn this ability as a 1st level spell (Knowledge: Arcana DC 17).</p>",
          "instructions": ""
        },
        "actions": [
          {
            "name": "Terror Touch",
            "actionType": "save",
            "activation": {
              "cost": 1,
              "type": "standard",
              "unchained": {
                "cost": 1,
                "type": "action"
              }
            },
            "range": {
              "value": 35,
              "units": "ft"
            },
            "target": {
              "value": ""
            },
            "attackBonus": "",
            "touch": false,
            "damage": {
              "critParts": [],
              "nonCritParts": [],
              "parts": []
            },
            "save": {
              "dc": "10 + floor(@attributes.hd.total / 2) + @abilities.cha.mod",
              "type": "will",
              "description": ""
            },
            "notes": {
              "effect": [
                "Duration: 1d4 rounds",
                "Recharge [[1d4]] rounds."
              ],
              "footer": []
            },
            "effectNotes": [
              "Duration: 1d4 rounds",
              "Recharge [[1d4]] rounds."
            ],
            "measureTemplate": {
              "type": "",
              "size": null
            }
          }
        ],
        "attackNotes": [],
        "effectNotes": [],
        "uses": {
          "value": 1,
          "per": "",
          "maxFormula": "1",
          "rechargeFormula": "1d4",
          "rechargePeriod": "rounds"
        },
        "changes": [],
        "contextNotes": [],
        "links": {
          "charges": []
        },
        "tag": "terror-touch",
        "subType": "racial",
        "traitType": "",
        "traitCategory": "",
        "racePoints": null,
        "abilityType": "su",
        "associations": {
          "classes": []
        },
        "showInQuickbar": false,
        "crOffset": "",
        "inherited": false,
        "acquired": false,
        "simple": false,
        "summons": false,
        "disabled": false,
        "classSkills": {}
      },
      "flags": {
        "ffd20-bestiary-builder": {
          "specialAbility": {
            "category": "toggle",
            "buff": null,
            "uses": {
              "value": 1,
              "per": "",
              "maxFormula": "1",
              "rechargeFormula": "1d4",
              "rechargePeriod": "rounds"
            },
            "saveDCs": [
              {
                "save": "will",
                "dc": 13,
                "raw": "Will save (DC 13)",
                "formula": "10 + floor(@attributes.hd.total / 2) + @abilities.cha.mod",
                "ability": "cha",
                "confidence": "default-su-cha-floor",
                "base": 11,
                "expectedDc": 13
              }
            ],
            "damages": [],
            "healing": [],
            "attack": null,
            "activation": {
              "cost": 1,
              "type": "standard",
              "unchained": {
                "cost": 1,
                "type": "action"
              }
            },
            "criticalAttack": null,
            "requiresSave": false,
            "saveType": "will",
            "blueMage": "Blue mages may learn this ability as a 1st level spell (Knowledge: Arcana DC 17).",
            "range": {
              "value": 35,
              "units": "ft"
            },
            "target": {
              "value": ""
            },
            "duration": {
              "duration": "1d4",
              "units": "rounds"
            },
            "abilityScores": {
              "str": {
                "value": 10,
                "mod": 0,
                "missing": false,
                "raw": "10"
              },
              "dex": {
                "value": 16,
                "mod": 3,
                "missing": false,
                "raw": "16"
              },
              "con": {
                "value": 10,
                "mod": 0,
                "missing": false,
                "raw": "10"
              },
              "int": {
                "value": 9,
                "mod": -1,
                "missing": false,
                "raw": "9"
              },
              "wis": {
                "value": 8,
                "mod": -1,
                "missing": false,
                "raw": "8"
              },
              "cha": {
                "value": 14,
                "mod": 2,
                "missing": false,
                "raw": "14"
              }
            },
            "sourceType": "Su"
          }
        }
      }
    },
    {
      "_id": "bf00000000000001",
      "name": "See in Darkness",
      "type": "buff",
      "img": "systems/ffd20/icons/spells/protect-sky-2.jpg",
      "system": {
        "description": {
          "value": "<p>A black dragon can see perfectly in darkness of any kind, including that created by the blacklight spell.</p>",
          "instructions": ""
        },
        "actions": [],
        "attackNotes": [],
        "effectNotes": [],
        "uses": {
          "value": null,
          "per": "",
          "autoDeductChargesCost": "",
          "maxFormula": "",
          "rechargeFormula": ""
        },
        "changes": [],
        "changeFlags": {
          "immuneToMorale": false,
          "loseDexToAC": false,
          "noMediumEncumbrance": false,
          "noHeavyEncumbrance": false,
          "mediumArmorFullSpeed": false,
          "heavyArmorFullSpeed": false,
          "lowLightVision": false,
          "seeInvisibility": false,
          "seeInDarkness": false
        },
        "contextNotes": [
          {
            "target": "misc",
            "text": "Can see perfectly in darkness, including magical darkness."
          }
        ],
        "links": {
          "children": []
        },
        "tag": "see-in-darkness",
        "subType": "perm",
        "active": true,
        "level": 0,
        "duration": {
          "value": null,
          "units": "",
          "end": ""
        },
        "conditions": [],
        "hideFromToken": false,
        "scriptCalls": []
      },
      "flags": {
        "ffd20-bestiary-builder": {
          "generatedBuff": {
            "sourceAbility": "See in Darkness",
            "category": "passive",
            "automationNotes": []
          }
        }
      }
    }
  ],
  "prototypeToken": {
    "name": "Hatchling Black Dragon",
    "actorLink": false,
    "disposition": -1,
    "texture": {
      "src": "modules/ffd20-expanded-bestiary/assets/creatures/hatchling-black-dragon.png"
    },
    "sight": {
      "enabled": true
    }
  },
  "flags": {
    "ffd20-bestiary-builder": {
      "sourceUrl": "https://finalfantasyd20.com/gamemastering/bestiary/dragons/dragon-family/black-dragon/hatchling-black-dragon/",
      "sourceImage": "https://www.finalfantasyd20.com/wp-content/uploads/hatch-blk-drg.png",
      "packagedImage": "modules/ffd20-expanded-bestiary/assets/creatures/hatchling-black-dragon.png",
      "parsed": {
        "alignment": "N/NE",
        "creatureType": "Dragon",
        "subtypes": [
          "Shadow"
        ],
        "xp": 600,
        "aura": "",
        "perception": 6,
        "offense": {
          "raw": [
            "Speed 60 ft., fly 100 ft. (average)",
            "Melee Bite +5 (1d4), 2 Claws +5 (1d3)",
            "Space 2.5 ft.; Reach 0 ft. (2.5 ft. with bite)",
            "Special Attacks Breath Weapon (30-ft. line, 1d10 shadow damage, Reflex DC 11 half, usable every 1d4 rounds) Special Abilities Terror Touch"
          ],
          "speed": "60 ft., fly 100 ft. (average)",
          "melee": "Bite +5 (1d4), 2 Claws +5 (1d3)",
          "ranged": "",
          "space": "Space 2.5 ft.; Reach 0 ft. (2.5 ft. with bite)",
          "specialAttacks": "Breath Weapon (30-ft. line, 1d10 shadow damage, Reflex DC 11 half, usable every 1d4 rounds)",
          "spellLines": []
        },
        "defense": {
          "raw": [
            "AC 16, touch 15, flat-footed 13 (+3 dex, +1 natural, +2 size)",
            "hp 25 (3d12)",
            "Fort +3, Ref +8, Will +2",
            "Immune Shadow, Paralysis, Sleep",
            "Weakness Holy"
          ],
          "ac": "AC 16, touch 15, flat-footed 13 (+3 dex, +1 natural, +2 size)",
          "hp": "hp 25 (3d12)",
          "hitPoints": 25,
          "hitDice": 3,
          "saves": "Fort +3, Ref +8, Will +2",
          "defensiveAbilities": "",
          "dr": "",
          "immunities": "Shadow, Paralysis, Sleep",
          "resistances": "",
          "weaknesses": "Holy",
          "sr": null
        },
        "statistics": [
          "Str 10, Dex 16, Con 10, Int 9, Wis 8, Cha 14",
          "Base Atk +3; CMB +4; CMD 14 (18 vs. trip)",
          "Feats Improved Initiative, Lightning Reflexes",
          "Skills Fly +13, Perception +6, Spellcraft +5, Stealth +21, Survival +5; Racial Modifiers +8 Stealth",
          "Languages Draconic"
        ],
        "gear": [],
        "tactics": [],
        "ecology": []
      }
    }
  }
}